astronomo/__init__.py
astronomo/astronomo_app.py
astronomo/astronomo_app.tcss
astronomo/bookmarks.py
astronomo/config.py
astronomo/emoji_utils.py
astronomo/feed_fetcher.py
astronomo/feeds.py
astronomo/formatters/__init__.py
astronomo/formatters/finger.py
astronomo/formatters/gopher.py
astronomo/formatters/nex.py
astronomo/formatters/spartan.py
astronomo/history.py
astronomo/identities.py
astronomo/image_cache.py
astronomo/media_detector.py
astronomo/opml.py
astronomo/parser.py
astronomo/response_handler.py
astronomo/screens/__init__.py
astronomo/screens/feeds.py
astronomo/screens/settings.py
astronomo/syntax.py
astronomo/tabs.py
astronomo/widgets/__init__.py
astronomo/widgets/add_bookmark_modal.py
astronomo/widgets/bookmarks_sidebar.py
astronomo/widgets/certificate_changed_modal.py
astronomo/widgets/certificate_details_modal.py
astronomo/widgets/certificates/__init__.py
astronomo/widgets/certificates/certificates.tcss
astronomo/widgets/certificates/confirm_delete_modal.py
astronomo/widgets/certificates/create_modal.py
astronomo/widgets/certificates/edit_modal.py
astronomo/widgets/certificates/file_picker_modal.py
astronomo/widgets/certificates/import_custom_modal.py
astronomo/widgets/certificates/import_lagrange_modal.py
astronomo/widgets/certificates/manage_urls_modal.py
astronomo/widgets/color_picker.py
astronomo/widgets/edit_item_modal.py
astronomo/widgets/feeds/__init__.py
astronomo/widgets/feeds/add_feed_modal.py
astronomo/widgets/feeds/add_folder_modal.py
astronomo/widgets/feeds/confirm_delete_modal.py
astronomo/widgets/feeds/edit_feed_modal.py
astronomo/widgets/feeds/edit_folder_modal.py
astronomo/widgets/feeds/opml_export_modal.py
astronomo/widgets/feeds/opml_import_modal.py
astronomo/widgets/gemtext_image.py
astronomo/widgets/gemtext_viewer.py
astronomo/widgets/identity_error_modal.py
astronomo/widgets/identity_select_modal.py
astronomo/widgets/input_modal.py
astronomo/widgets/navigation.py
astronomo/widgets/quick_navigation_modal.py
astronomo-0.16.0.dist-info/WHEEL
astronomo-0.16.0.dist-info/entry_points.txt
astronomo-0.16.0.dist-info/METADATA
astronomo-0.16.0.dist-info/RECORD
