Metadata-Version: 2.4
Name: astronomo
Version: 0.16.0
Summary: A modern Gemini browser for the terminal
Author: Alan Velasco
Author-email: Alan Velasco <alan@alanbato.com>
License-Expression: GPL-3.0-or-later
Requires-Dist: emoji>=2.0.0
Requires-Dist: feedparser>=6.0.0
Requires-Dist: humanize>=4.0.0
Requires-Dist: nauyaca>=0.1.0
Requires-Dist: textual[syntax]>=6.6.0
Requires-Dist: tomli-w>=1.0.0
Requires-Dist: tomli>=2.0.0 ; python_full_version < '3.11'
Requires-Dist: typing-extensions>=4.0.0 ; python_full_version < '3.11'
Requires-Dist: typer>=0.20.0
Requires-Dist: mapilli>=0.1.1
Requires-Dist: mototli>=0.1.1
Requires-Dist: teyaotlani>=0.1.3
Requires-Dist: chafa-py>=1.2.0 ; extra == 'chafa'
Requires-Python: >=3.10
Provides-Extra: chafa
